.gitignore
MANIFEST.in
README.rst
setup.cfg
setup.py
docs/HISTORY.txt
docs/LICENSE.GPL
docs/LICENSE.txt
docs/MANUAL.txt
raptus/__init__.py
raptus.article.maps.egg-info/PKG-INFO
raptus.article.maps.egg-info/SOURCES.txt
raptus.article.maps.egg-info/dependency_links.txt
raptus.article.maps.egg-info/entry_points.txt
raptus.article.maps.egg-info/namespace_packages.txt
raptus.article.maps.egg-info/not-zip-safe
raptus.article.maps.egg-info/requires.txt
raptus.article.maps.egg-info/top_level.txt
raptus/article/__init__.py
raptus/article/maps/__init__.py
raptus/article/maps/adapters.py
raptus/article/maps/config.py
raptus/article/maps/configure.zcml
raptus/article/maps/index.py
raptus/article/maps/interfaces.py
raptus/article/maps/overrides.zcml
raptus/article/maps/permissions.zcml
raptus/article/maps/browser/__init__.py
raptus/article/maps/browser/configure.zcml
raptus/article/maps/browser/map_icon.gif
raptus/article/maps/browser/maps.pt
raptus/article/maps/browser/maps.py
raptus/article/maps/browser/maps_full.gif
raptus/article/maps/browser/maps_left.gif
raptus/article/maps/browser/maps_right.gif
raptus/article/maps/browser/marker_icon.gif
raptus/article/maps/browser/overrides.zcml
raptus/article/maps/browser/view.pt
raptus/article/maps/browser/view.py
raptus/article/maps/content/__init__.py
raptus/article/maps/content/configure.zcml
raptus/article/maps/content/map.py
raptus/article/maps/content/marker.py
raptus/article/maps/i18n/raptus.article-de.mo
raptus/article/maps/i18n/raptus.article-de.po
raptus/article/maps/i18n/raptus.article-fr.mo
raptus/article/maps/i18n/raptus.article-fr.po
raptus/article/maps/i18n/raptus.article.pot
raptus/article/maps/profiles/default/cssregistry.xml
raptus/article/maps/profiles/default/factorytool.xml
raptus/article/maps/profiles/default/jsregistry.xml
raptus/article/maps/profiles/default/metadata.xml
raptus/article/maps/profiles/default/propertiestool.xml
raptus/article/maps/profiles/default/rolemap.xml
raptus/article/maps/profiles/default/skins.xml
raptus/article/maps/profiles/default/types.xml
raptus/article/maps/profiles/default/viewlets.xml
raptus/article/maps/profiles/default/workflows.xml
raptus/article/maps/profiles/default/types/Article.xml
raptus/article/maps/profiles/default/types/Map.xml
raptus/article/maps/profiles/default/types/Marker.xml
