Metadata-Version: 1.1
Name: raptus.article.maps
Version: 2.0b18
Summary: Provides a maps content type to be added to articles
Home-page: https://github.com/Raptus/raptus.article.maps
Author: Raptus AG
Author-email: dev@raptus.com
License: GPL
Platform: UNKNOWN
Classifier: Programming Language :: Python
Classifier: Topic :: Software Development :: Libraries :: Python Modules
